curl_arguments_url/__init__.py
curl_arguments_url/cli.py
curl_arguments_url/curl_arguments_url.py
curl_arguments_url/yaml.py
curl_arguments_url/models/__init__.py
curl_arguments_url/models/methods.py
curl_arguments_url/models/open_api.py
curl_arguments_url-0.1.4.dist-info/AUTHORS.rst
curl_arguments_url-0.1.4.dist-info/LICENSE
curl_arguments_url-0.1.4.dist-info/METADATA
curl_arguments_url-0.1.4.dist-info/WHEEL
curl_arguments_url-0.1.4.dist-info/entry_points.txt
curl_arguments_url-0.1.4.dist-info/top_level.txt
curl_arguments_url-0.1.4.dist-info/RECORD
