Metadata-Version: 2.1
Name: curl-arguments-url
Version: 0.1.4
Summary: Curl with Arguments for Url
Home-page: https://github.com/valmikirao/curl_arguments_url
Author: Valmiki Rao
Author-email: valmikirao@gmail.com
License: Apache Software License 2.0
Keywords: curl_arguments_url,carl,curl,zsh,completions,swagger,openapi
Classifier: Development Status :: 2 - Pre-Alpha
Classifier: Intended Audience :: Developers
Classifier: License :: OSI Approved :: Apache Software License
Classifier: Natural Language :: English
Classifier: Programming Language :: Python :: 3.7
Classifier: Programming Language :: Python :: 3.8
Classifier: Programming Language :: Python :: 3.9
Classifier: Programming Language :: Python :: 3.10
Classifier: Programming Language :: Python :: 3.11
Requires-Python: >=3.7
License-File: LICENSE
License-File: AUTHORS.rst
Requires-Dist: PyYAML (<7.0.0,>=6.0.0)
Requires-Dist: jsonref (<2.0.0,>=1.1.0)
Requires-Dist: pydantic (<2.0.0,>=1.10.7)
Provides-Extra: ryaml
Requires-Dist: ryaml (<1.0.0,>=0.4.0) ; extra == 'ryaml'
